{
  "schemaVersion": "1.0",
  "skillCode": "N1.4",
  "skillName": "Use and interpret inequalities in context (incl number lines and statements)",
  "routeType": "C",
  "routeLabel": "Misconception-corrective",
  "misconceptionSummary": "Students reverse inequality direction when ordering mixed negatives and zero.",
  "generatedAt": "2026-04-18T00:00:00.000Z",
  "steps": [
    {
      "stepIndex": 0,
      "id": "show-error",
      "visuals": [
        {
          "type": "step_reveal",
          "lines": [
            { "text": "Order ascending: -7, 0, -3, 2", "highlight": null },
            { "text": "Student writes: 0, -3, -7, 2  ✗", "highlight": "accent" },
            { "text": "Error: placed negatives after zero", "highlight": "dim" }
          ]
        }
      ],
      "narration": "The student put zero first, then the negatives. But negative numbers are all less than zero — they all belong to the left of zero on the number line.",
      "audioFile": null
    },
    {
      "stepIndex": 1,
      "id": "number-line-all",
      "visuals": [
        {
          "type": "number_line",
          "range": [-8, 3],
          "highlightStart": -7,
          "arrowFrom": -7,
          "arrowTo": 2
        }
      ],
      "narration": "Plot all four values on the line. Reading from left to right gives the ascending order automatically. Notice all negatives are to the left of zero.",
      "audioFile": null
    },
    {
      "stepIndex": 2,
      "id": "correct-order",
      "visuals": [
        {
          "type": "step_reveal",
          "lines": [
            { "text": "Leftmost (smallest): -7",   "highlight": null },
            { "text": "Next:                -3",   "highlight": null },
            { "text": "Then:                 0",   "highlight": null },
            { "text": "Rightmost (largest):  2",   "highlight": "green" }
          ]
        }
      ],
      "narration": "All negatives come before zero. Among the negatives, the more negative value — further from zero — comes first. Then zero. Then all positives.",
      "audioFile": null
    },
    {
      "stepIndex": 3,
      "id": "result",
      "visuals": [
        {
          "type": "result_reveal",
          "expression": "-7, -3, 0, 2",
          "label": "Ascending order: negatives → zero → positives"
        }
      ],
      "narration": "Negative seven, negative three, zero, two. The number line reads left to right — and that order is always ascending.",
      "audioFile": null
    }
  ],
  "misconceptionStrip": {
    "text": "Common mistake: placing negatives after zero in ascending order. All negatives are less than zero — they all go to the left of it.",
    "audioNarration": "In ascending order, negatives always come first. Zero is in the middle. Positives come last. The number line shows this immediately."
  },
  "loopable": true,
  "pauseAtEndMs": 2000
}
